modbusy/__init__.py
modbusy/csvslave.py
modbusy/py.typed
modbusy-1.1.0.dist-info/LICENSE
modbusy-1.1.0.dist-info/METADATA
modbusy-1.1.0.dist-info/WHEEL
modbusy-1.1.0.dist-info/top_level.txt
modbusy-1.1.0.dist-info/zip-safe
modbusy-1.1.0.dist-info/RECORD
