Metadata-Version: 2.1
Name: modbusy
Version: 1.1.0
Summary: Easy library for writing Modbus slaves
Home-page: https://bitbucket.com/8minutenergy/modbusy
Author: Brandon Carpenter
Author-email: brandon@8minute.com
License: BSD
Platform: UNKNOWN
Classifier: Development Status :: 4 - Beta
Classifier: Environment :: Console
Classifier: Intended Audience :: Developers
Classifier: License :: OSI Approved :: BSD License
Classifier: Operating System :: OS Independent
Classifier: Programming Language :: Python :: 3.6
Classifier: Programming Language :: Python :: 3.7
Classifier: Programming Language :: Python :: 3.8
Classifier: Programming Language :: Python :: 3.9
Classifier: Topic :: Software Development :: Embedded Systems
Classifier: Typing :: Typed
Requires-Python: >=3.6
License-File: LICENSE
Requires-Dist: gevent (>=1.3)
Requires-Dist: uModbus (>=1)
Provides-Extra: cli
Requires-Dist: click (>=6) ; extra == 'cli'
Requires-Dist: pyyaml ; extra == 'cli'
Requires-Dist: voluptuous ; extra == 'cli'
Provides-Extra: mypy
Requires-Dist: mypy (>=0.910) ; extra == 'mypy'
Requires-Dist: types-PyYAML ; extra == 'mypy'
Provides-Extra: test
Requires-Dist: pytest (>5.0) ; extra == 'test'
